[
    {
        "action": "RESET",
        "time": "12:01:38",
        "time_int": 43298,
        "user": "",
        "content": "027001HHHIIIGGIGGIGJIJJHGHFGHJFHJJJKKIKJLHIKFIHKKKGEEJGKFKHG"
    },
    {
        "action": "LOAD",
        "time": "12:01:38",
        "time_int": 43298,
        "user": "",
        "content": "8889997797797a9aa878678a68aaabb9bac89b698bbb755a7b6b87"
    },
    {
        "action": "GOTO",
        "time": "12:01:38",
        "time_int": 43298,
        "user": "",
        "content": 1
    },
    {
        "action": "TALK",
        "time": "12:01:49",
        "time_int": 43309,
        "user": "Guest870",
        "content": "请问今晚的老师是？"
    },
    {
        "action": "MOVE",
        "time": "12:02:01",
        "time_int": 43321,
        "user": "GrandMaster",
        "content": "99"
    },
    {
        "action": "TALK",
        "time": "12:02:04",
        "time_int": 43324,
        "user": "zjrenju92",
        "content": "朱建锋老师"
    },
    {
        "action": "TALK",
        "time": "12:02:38",
        "time_int": 43358,
        "user": "tommy",
        "content": "呵呵，今天老大没有分"
    },
    {
        "action": "TALK",
        "time": "12:02:41",
        "time_int": 43361,
        "user": "GrandMaster",
        "content": "今天继续来看恒星局"
    },
    {
        "action": "MOVE",
        "time": "12:02:46",
        "time_int": 43366,
        "user": "GrandMaster",
        "content": "a8"
    },
    {
        "action": "MOVE",
        "time": "12:02:50",
        "time_int": 43370,
        "user": "GrandMaster",
        "content": "97"
    },
    {
        "action": "MOVE",
        "time": "12:02:55",
        "time_int": 43375,
        "user": "GrandMaster",
        "content": "9a"
    },
    {
        "action": "MOVE",
        "time": "12:03:01",
        "time_int": 43381,
        "user": "GrandMaster",
        "content": "a9"
    },
    {
        "action": "MOVE",
        "time": "12:03:05",
        "time_int": 43385,
        "user": "GrandMaster",
        "content": "ba"
    },
    {
        "action": "MOVE",
        "time": "12:03:09",
        "time_int": 43389,
        "user": "GrandMaster",
        "content": "ab"
    },
    {
        "action": "MOVE",
        "time": "12:03:13",
        "time_int": 43393,
        "user": "GrandMaster",
        "content": "96"
    },
    {
        "action": "MOVE",
        "time": "12:03:20",
        "time_int": 43400,
        "user": "GrandMaster",
        "content": "87"
    },
    {
        "action": "MOVE",
        "time": "12:03:34",
        "time_int": 43414,
        "user": "GrandMaster",
        "content": "b8"
    },
    {
        "action": "MOVE",
        "time": "12:03:53",
        "time_int": 43433,
        "user": "GrandMaster",
        "content": "c8"
    },
    {
        "action": "TALK",
        "time": "12:04:03",
        "time_int": 43443,
        "user": "GrandMaster",
        "content": "先来看这个12"
    },
    {
        "action": "TALK",
        "time": "12:04:14",
        "time_int": 43454,
        "user": "Guest863",
        "content": "哦"
    },
    {
        "action": "TALK",
        "time": "12:04:23",
        "time_int": 43463,
        "user": "zjrenju92",
        "content": "。"
    },
    {
        "action": "TALK",
        "time": "12:05:11",
        "time_int": 43511,
        "user": "GrandMaster",
        "content": "这个12以后黑棋现在可以说 在右边应该没有什么直接的杀了。。"
    },
    {
        "action": "TALK",
        "time": "12:06:03",
        "time_int": 43563,
        "user": "GrandMaster",
        "content": "那么现在我们要看黑棋右边能如何尽量既交换的干净。又能往别的地方转移尽量大的优势"
    },
    {
        "action": "TALK",
        "time": "12:06:51",
        "time_int": 43611,
        "user": "GrandMaster",
        "content": "这里很明显有几个黑棋活三后白棋的唯一"
    },
    {
        "action": "TALK",
        "time": "12:07:00",
        "time_int": 43620,
        "user": "GrandMaster",
        "content": "比如先活j10那么h10是唯一"
    },
    {
        "action": "TALK",
        "time": "12:07:10",
        "time_int": 43630,
        "user": "GrandMaster",
        "content": "先j7那么l9反是唯一"
    },
    {
        "action": "TALK",
        "time": "12:07:14",
        "time_int": 43634,
        "user": "zjrenju06",
        "content": "嘿嘿~~~GM今天讲什么呀"
    },
    {
        "action": "TALK",
        "time": "12:07:21",
        "time_int": 43641,
        "user": "GrandMaster",
        "content": "k9活三的话k7是唯一等等"
    },
    {
        "action": "TALK",
        "time": "12:07:22",
        "time_int": 43642,
        "user": "zjrenju92",
        "content": "对"
    },
    {
        "action": "TALK",
        "time": "12:07:38",
        "time_int": 43658,
        "user": "zjrenju06",
        "content": "已经开始了呀，来晚了啦，哭哭～｀"
    },
    {
        "action": "TALK",
        "time": "12:07:43",
        "time_int": 43663,
        "user": "GrandMaster",
        "content": "既然刚才我们讲过现在的黑棋进攻方向和思路"
    },
    {
        "action": "TALK",
        "time": "12:07:52",
        "time_int": 43672,
        "user": "GrandMaster",
        "content": "那么就照着前面的思路现在来开始选择交换方法"
    },
    {
        "action": "TALK",
        "time": "12:08:01",
        "time_int": 43681,
        "user": "Guest871",
        "content": "开始了我也能进奇怪？"
    },
    {
        "action": "TALK",
        "time": "12:08:17",
        "time_int": 43697,
        "user": "zjrenju50",
        "content": "GM忘记锁门勒"
    },
    {
        "action": "TALK",
        "time": "12:08:29",
        "time_int": 43709,
        "user": "Guest871",
        "content": "谢谢老师"
    },
    {
        "action": "TALK",
        "time": "12:08:32",
        "time_int": 43712,
        "user": "GrandMaster",
        "content": "既然要放弃右边。。"
    },
    {
        "action": "TALK",
        "time": "12:08:39",
        "time_int": 43719,
        "user": "zjrenju92",
        "content": "好·"
    },
    {
        "action": "MOVE",
        "time": "12:08:49",
        "time_int": 43729,
        "user": "GrandMaster",
        "content": "a7"
    },
    {
        "action": "TALK",
        "time": "12:09:02",
        "time_int": 43742,
        "user": "GrandMaster",
        "content": "那么这里可以选择先活j7或者k9"
    },
    {
        "action": "MOVE",
        "time": "12:09:09",
        "time_int": 43749,
        "user": "GrandMaster",
        "content": "c9"
    },
    {
        "action": "TALK",
        "time": "12:09:16",
        "time_int": 43756,
        "user": "GrandMaster",
        "content": "白唯一"
    },
    {
        "action": "MOVE",
        "time": "12:09:20",
        "time_int": 43760,
        "user": "GrandMaster",
        "content": "b9"
    },
    {
        "action": "MOVE",
        "time": "12:09:36",
        "time_int": 43776,
        "user": "GrandMaster",
        "content": "b7"
    },
    {
        "action": "TALK",
        "time": "12:09:54",
        "time_int": 43794,
        "user": "GrandMaster",
        "content": "这几手白棋都是唯一防"
    },
    {
        "action": "TALK",
        "time": "12:10:02",
        "time_int": 43802,
        "user": "zjrenju92",
        "content": "是的！"
    },
    {
        "action": "TALK",
        "time": "12:10:35",
        "time_int": 43835,
        "user": "GrandMaster",
        "content": "再看看黑如果光靠现在的优势能不能追胜呢"
    },
    {
        "action": "TALK",
        "time": "12:10:59",
        "time_int": 43859,
        "user": "GrandMaster",
        "content": "伟鬼做运动呀？"
    },
    {
        "action": "TALK",
        "time": "12:11:15",
        "time_int": 43875,
        "user": "zjrenju92",
        "content": "现在好象很难胜！"
    },
    {
        "action": "TALK",
        "time": "12:11:16",
        "time_int": 43876,
        "user": "GrandMaster",
        "content": "大家看一下现在的黑棋"
    },
    {
        "action": "TALK",
        "time": "12:11:54",
        "time_int": 43914,
        "user": "GrandMaster",
        "content": "大家都觉得应该是没有胜吧"
    },
    {
        "action": "TALK",
        "time": "12:12:01",
        "time_int": 43921,
        "user": "zjrenju12",
        "content": "没有"
    },
    {
        "action": "TALK",
        "time": "12:12:02",
        "time_int": 43922,
        "user": "zjrenju92",
        "content": "恩"
    },
    {
        "action": "TALK",
        "time": "12:12:04",
        "time_int": 43924,
        "user": "tommy",
        "content": "嗯"
    },
    {
        "action": "TALK",
        "time": "12:12:25",
        "time_int": 43945,
        "user": "GrandMaster",
        "content": "白右边的两个活二。暂时来说是没有进攻力的。。"
    },
    {
        "action": "TALK",
        "time": "12:12:32",
        "time_int": 43952,
        "user": "GrandMaster",
        "content": "就算白怎么活应该都是杀不了的"
    },
    {
        "action": "TALK",
        "time": "12:12:47",
        "time_int": 43967,
        "user": "GrandMaster",
        "content": "但是黑棋现在只有一个活二。。几个眠三之间的联系也不是很好"
    },
    {
        "action": "TALK",
        "time": "12:13:13",
        "time_int": 43993,
        "user": "GrandMaster",
        "content": "黑棋那个二也不太好动。。那么黑棋就该来选择做棋了。"
    },
    {
        "action": "TALK",
        "time": "12:13:39",
        "time_int": 44019,
        "user": "GrandMaster",
        "content": "这里有没有什么好的建议？大家觉得现在做哪比较舒服？"
    },
    {
        "action": "TALK",
        "time": "12:13:43",
        "time_int": 44023,
        "user": "zjrenju12",
        "content": "老师g6可以吗？"
    },
    {
        "action": "TALK",
        "time": "12:13:49",
        "time_int": 44029,
        "user": "zjrenju88",
        "content": "G6？"
    },
    {
        "action": "TALK",
        "time": "12:14:01",
        "time_int": 44041,
        "user": "zjrenju12",
        "content": "对"
    },
    {
        "action": "TALK",
        "time": "12:14:29",
        "time_int": 44069,
        "user": "zjrenju12",
        "content": "不可以吗？"
    },
    {
        "action": "TALK",
        "time": "12:14:31",
        "time_int": 44071,
        "user": "GrandMaster",
        "content": "这里做任何一个点都是可行的"
    },
    {
        "action": "TALK",
        "time": "12:14:38",
        "time_int": 44078,
        "user": "zjrenju88",
        "content": "。。。"
    },
    {
        "action": "TALK",
        "time": "12:14:47",
        "time_int": 44087,
        "user": "GrandMaster",
        "content": "但是要看哪个点比较好"
    },
    {
        "action": "TALK",
        "time": "12:15:10",
        "time_int": 44110,
        "user": "zjrenju88",
        "content": "G10？"
    },
    {
        "action": "TALK",
        "time": "12:15:31",
        "time_int": 44131,
        "user": "GrandMaster",
        "content": "太急了。。g10白直接i8的话基本上下连接就比较困难了。"
    },
    {
        "action": "TALK",
        "time": "12:15:47",
        "time_int": 44147,
        "user": "zjrenju88",
        "content": "哦"
    },
    {
        "action": "TALK",
        "time": "12:15:55",
        "time_int": 44155,
        "user": "GrandMaster",
        "content": "这里就比较考验大家局部的计算力"
    },
    {
        "action": "TALK",
        "time": "12:16:10",
        "time_int": 44170,
        "user": "zjrenju92",
        "content": "J10"
    },
    {
        "action": "TALK",
        "time": "12:16:16",
        "time_int": 44176,
        "user": "GrandMaster",
        "content": "首先黑棋思路很明确。要在左边饶着进攻"
    },
    {
        "action": "TALK",
        "time": "12:16:20",
        "time_int": 44180,
        "user": "zjrenju12",
        "content": "j6"
    },
    {
        "action": "TALK",
        "time": "12:16:26",
        "time_int": 44186,
        "user": "GrandMaster",
        "content": "j10的话是很亏的走法"
    },
    {
        "action": "TALK",
        "time": "12:16:32",
        "time_int": 44192,
        "user": "GrandMaster",
        "content": "直接被白h10后"
    },
    {
        "action": "TALK",
        "time": "12:16:37",
        "time_int": 44197,
        "user": "GrandMaster",
        "content": "黑右上的棋杀不掉"
    },
    {
        "action": "TALK",
        "time": "12:16:47",
        "time_int": 44207,
        "user": "GrandMaster",
        "content": "而且再想和左边联系几乎不可能"
    },
    {
        "action": "TALK",
        "time": "12:16:47",
        "time_int": 44207,
        "user": "zjrenju88",
        "content": "看起来G6不错"
    },
    {
        "action": "TALK",
        "time": "12:16:56",
        "time_int": 44216,
        "user": "zjrenju12",
        "content": "我个人觉得g6不错"
    },
    {
        "action": "TALK",
        "time": "12:16:58",
        "time_int": 44218,
        "user": "GrandMaster",
        "content": "j6应该这里算最好的点了。"
    },
    {
        "action": "TALK",
        "time": "12:17:02",
        "time_int": 44222,
        "user": "GrandMaster",
        "content": "恩。g6是可以"
    },
    {
        "action": "TALK",
        "time": "12:17:04",
        "time_int": 44224,
        "user": "zjrenju92",
        "content": "K6"
    },
    {
        "action": "TALK",
        "time": "12:17:07",
        "time_int": 44227,
        "user": "GrandMaster",
        "content": "但是不是太好"
    },
    {
        "action": "MOVE",
        "time": "12:17:09",
        "time_int": 44229,
        "user": "GrandMaster",
        "content": "a6"
    },
    {
        "action": "TALK",
        "time": "12:17:33",
        "time_int": 44253,
        "user": "GrandMaster",
        "content": "这里我们来看看为什么说j6比起g6来说更好呢"
    },
    {
        "action": "TALK",
        "time": "12:17:46",
        "time_int": 44266,
        "user": "zjrenju50",
        "content": "GM 点名不？"
    },
    {
        "action": "TALK",
        "time": "12:17:54",
        "time_int": 44274,
        "user": "zjrenju50",
        "content": "俺要找水喝勒~"
    },
    {
        "action": "TALK",
        "time": "12:17:56",
        "time_int": 44276,
        "user": "GrandMaster",
        "content": "首先如果走g6那么肯定白防一手之后黑j6基本没什么效果了。"
    },
    {
        "action": "TALK",
        "time": "12:18:09",
        "time_int": 44289,
        "user": "GrandMaster",
        "content": "你什么时候去找水啊通知我一下，我来点名"
    },
    {
        "action": "TALK",
        "time": "12:18:20",
        "time_int": 44300,
        "user": "zjrenju50",
        "content": "-_-!!"
    },
    {
        "action": "TALK",
        "time": "12:18:22",
        "time_int": 44302,
        "user": "tommy",
        "content": "嗯，今天朱老师没有一上来就点名"
    },
    {
        "action": "TALK",
        "time": "12:18:24",
        "time_int": 44304,
        "user": "zjrenju12",
        "content": "那白走g6呢"
    },
    {
        "action": "TALK",
        "time": "12:18:43",
        "time_int": 44323,
        "user": "GrandMaster",
        "content": "恩。。这里我们就看一下如果现在白走g6黑有没有棋"
    },
    {
        "action": "TALK",
        "time": "12:18:50",
        "time_int": 44330,
        "user": "GrandMaster",
        "content": "这样一比较就能看出好坏了。"
    },
    {
        "action": "MOVE",
        "time": "12:18:53",
        "time_int": 44333,
        "user": "GrandMaster",
        "content": "76"
    },
    {
        "action": "MOVE",
        "time": "12:19:00",
        "time_int": 44340,
        "user": "GrandMaster",
        "content": "b6"
    },
    {
        "action": "TALK",
        "time": "12:19:12",
        "time_int": 44352,
        "user": "zjrenju12",
        "content": "i8"
    },
    {
        "action": "TALK",
        "time": "12:19:14",
        "time_int": 44354,
        "user": "GrandMaster",
        "content": "现在白只能i8冲掉吧"
    },
    {
        "action": "MOVE",
        "time": "12:19:15",
        "time_int": 44355,
        "user": "GrandMaster",
        "content": "98"
    },
    {
        "action": "MOVE",
        "time": "12:19:18",
        "time_int": 44358,
        "user": "GrandMaster",
        "content": "65"
    },
    {
        "action": "MOVE",
        "time": "12:19:22",
        "time_int": 44362,
        "user": "GrandMaster",
        "content": "c6"
    },
    {
        "action": "TALK",
        "time": "12:19:26",
        "time_int": 44366,
        "user": "zjrenju92",
        "content": "J6好象 成了个2又弄个眠三而且还防守了白一个活2，太妙了，找不到比这个再好的便宜了！！"
    },
    {
        "action": "MOVE",
        "time": "12:19:29",
        "time_int": 44369,
        "user": "GrandMaster",
        "content": "a5"
    },
    {
        "action": "MOVE",
        "time": "12:19:34",
        "time_int": 44374,
        "user": "GrandMaster",
        "content": "a4"
    },
    {
        "action": "MOVE",
        "time": "12:19:38",
        "time_int": 44378,
        "user": "GrandMaster",
        "content": "c7"
    },
    {
        "action": "TALK",
        "time": "12:19:40",
        "time_int": 44380,
        "user": "zjrenju88",
        "content": "H3"
    },
    {
        "action": "TALK",
        "time": "12:19:43",
        "time_int": 44383,
        "user": "GrandMaster",
        "content": "确实"
    },
    {
        "action": "TALK",
        "time": "12:19:48",
        "time_int": 44388,
        "user": "zjrenju12",
        "content": "i4"
    },
    {
        "action": "TALK",
        "time": "12:19:54",
        "time_int": 44394,
        "user": "GrandMaster",
        "content": "从效果来说j6也是比较稳的点"
    },
    {
        "action": "MOVE",
        "time": "12:19:57",
        "time_int": 44397,
        "user": "GrandMaster",
        "content": "94"
    },
    {
        "action": "MOVE",
        "time": "12:20:01",
        "time_int": 44401,
        "user": "GrandMaster",
        "content": "e9"
    },
    {
        "action": "MOVE",
        "time": "12:20:06",
        "time_int": 44406,
        "user": "GrandMaster",
        "content": "d8"
    },
    {
        "action": "MOVE",
        "time": "12:20:09",
        "time_int": 44409,
        "user": "GrandMaster",
        "content": "da"
    },
    {
        "action": "TALK",
        "time": "12:20:29",
        "time_int": 44429,
        "user": "GrandMaster",
        "content": "从下面饶到上面了。。"
    },
    {
        "action": "TALK",
        "time": "12:20:34",
        "time_int": 44434,
        "user": "GrandMaster",
        "content": "现在黑两套vcf"
    },
    {
        "action": "TALK",
        "time": "12:20:35",
        "time_int": 44435,
        "user": "zjrenju12",
        "content": "l11"
    },
    {
        "action": "TALK",
        "time": "12:20:41",
        "time_int": 44441,
        "user": "zjrenju92",
        "content": "恩，看到了"
    },
    {
        "action": "TALK",
        "time": "12:20:44",
        "time_int": 44444,
        "user": "GrandMaster",
        "content": "这里的唯一防是j13"
    },
    {
        "action": "TALK",
        "time": "12:20:53",
        "time_int": 44453,
        "user": "GrandMaster",
        "content": "l11的话黑l10，n10，n12"
    },
    {
        "action": "TALK",
        "time": "12:20:56",
        "time_int": 44456,
        "user": "GrandMaster",
        "content": "vcf杀了。"
    },
    {
        "action": "MOVE",
        "time": "12:20:59",
        "time_int": 44459,
        "user": "GrandMaster",
        "content": "ad"
    },
    {
        "action": "TALK",
        "time": "12:21:03",
        "time_int": 44463,
        "user": "zjrenju92",
        "content": "J13有个反可惜不太管用"
    },
    {
        "action": "TALK",
        "time": "12:21:03",
        "time_int": 44463,
        "user": "zjrenju12",
        "content": "看到了"
    },
    {
        "action": "TALK",
        "time": "12:21:08",
        "time_int": 44468,
        "user": "GrandMaster",
        "content": "虽然这里反一下"
    },
    {
        "action": "TALK",
        "time": "12:21:14",
        "time_int": 44474,
        "user": "GrandMaster",
        "content": "但是由于k12黑没有冲"
    },
    {
        "action": "MOVE",
        "time": "12:21:16",
        "time_int": 44476,
        "user": "GrandMaster",
        "content": "ca"
    },
    {
        "action": "MOVE",
        "time": "12:21:19",
        "time_int": 44479,
        "user": "GrandMaster",
        "content": "aa"
    },
    {
        "action": "MOVE",
        "time": "12:21:20",
        "time_int": 44480,
        "user": "GrandMaster",
        "content": "ac"
    },
    {
        "action": "TALK",
        "time": "12:21:26",
        "time_int": 44486,
        "user": "tommy",
        "content": "嗯"
    },
    {
        "action": "TALK",
        "time": "12:21:26",
        "time_int": 44486,
        "user": "zjrenju92",
        "content": "K11还是个杀"
    },
    {
        "action": "TALK",
        "time": "12:21:37",
        "time_int": 44497,
        "user": "GrandMaster",
        "content": "所以到这里"
    },
    {
        "action": "TALK",
        "time": "12:21:46",
        "time_int": 44506,
        "user": "GrandMaster",
        "content": "黑还是双杀了。"
    },
    {
        "action": "TALK",
        "time": "12:22:03",
        "time_int": 44523,
        "user": "tommy",
        "content": "呵呵，厉害，这个27我想不出来"
    },
    {
        "action": "GOTO",
        "time": "12:22:14",
        "time_int": 44534,
        "user": "GrandMaster",
        "content": 17
    },
    {
        "action": "TALK",
        "time": "12:22:32",
        "time_int": 44552,
        "user": "GrandMaster",
        "content": "那么如果白防i8"
    },
    {
        "action": "TALK",
        "time": "12:22:36",
        "time_int": 44556,
        "user": "GrandMaster",
        "content": "和刚才的杀是一样的"
    },
    {
        "action": "TALK",
        "time": "12:22:43",
        "time_int": 44563,
        "user": "GrandMaster",
        "content": "这里我们就不摆i8这个防点了。"
    },
    {
        "action": "TALK",
        "time": "12:23:05",
        "time_int": 44585,
        "user": "zjrenju50",
        "content": "那就K6"
    },
    {
        "action": "TALK",
        "time": "12:23:06",
        "time_int": 44586,
        "user": "GrandMaster",
        "content": "所以说。"
    },
    {
        "action": "TALK",
        "time": "12:23:17",
        "time_int": 44597,
        "user": "GrandMaster",
        "content": "这个17白18只能跟着防在右边。。"
    },
    {
        "action": "TALK",
        "time": "12:23:35",
        "time_int": 44615,
        "user": "zjrenju92",
        "content": "L10？"
    },
    {
        "action": "TALK",
        "time": "12:23:53",
        "time_int": 44633,
        "user": "GrandMaster",
        "content": "所以。由于刚才这套计算。大家看到这里右下可以联系到右上有套杀"
    },
    {
        "action": "TALK",
        "time": "12:24:14",
        "time_int": 44654,
        "user": "GrandMaster",
        "content": "使得现在白棋18要防在右下这一块"
    },
    {
        "action": "TALK",
        "time": "12:24:39",
        "time_int": 44679,
        "user": "GrandMaster",
        "content": "那么从战略上来说。。黑棋右在下面占到了往左边转移优势的便宜"
    },
    {
        "action": "TALK",
        "time": "12:25:34",
        "time_int": 44734,
        "user": "GrandMaster",
        "content": "所以现在大家应该都能感觉这个17相对来说又稳而且也比较强"
    },
    {
        "action": "TALK",
        "time": "12:25:43",
        "time_int": 44743,
        "user": "zjrenju92",
        "content": "是的！"
    },
    {
        "action": "TALK",
        "time": "12:25:44",
        "time_int": 44744,
        "user": "tommy",
        "content": "嗯"
    },
    {
        "action": "TALK",
        "time": "12:26:06",
        "time_int": 44766,
        "user": "GrandMaster",
        "content": "我们接下来再看看单防的点"
    },
    {
        "action": "TALK",
        "time": "12:27:16",
        "time_int": 44836,
        "user": "GrandMaster",
        "content": "单防的话除了刚才看的防那不眠三之外。。别的防点就只有h6和k6了。"
    },
    {
        "action": "TALK",
        "time": "12:27:49",
        "time_int": 44869,
        "user": "zjrenju50",
        "content": "Attention please!"
    },
    {
        "action": "TALK",
        "time": "12:28:03",
        "time_int": 44883,
        "user": "zjrenju50",
        "content": "不点名-_-!!"
    },
    {
        "action": "MOVE",
        "time": "12:28:17",
        "time_int": 44897,
        "user": "GrandMaster",
        "content": "86"
    },
    {
        "action": "TALK",
        "time": "12:28:17",
        "time_int": 44897,
        "user": "Guest863",
        "content": "I am here!"
    },
    {
        "action": "TALK",
        "time": "12:28:25",
        "time_int": 44905,
        "user": "GrandMaster",
        "content": "先来看看h6吧"
    },
    {
        "action": "TALK",
        "time": "12:28:25",
        "time_int": 44905,
        "user": "zjrenju92",
        "content": "防I8行不行？"
    },
    {
        "action": "TALK",
        "time": "12:28:31",
        "time_int": 44911,
        "user": "GrandMaster",
        "content": "防i8不是说过了吗"
    },
    {
        "action": "TALK",
        "time": "12:28:37",
        "time_int": 44917,
        "user": "GrandMaster",
        "content": "和前面防g6是一样的杀法"
    },
    {
        "action": "BACK",
        "time": "12:28:41",
        "time_int": 44921,
        "user": "GrandMaster",
        "content": ""
    },
    {
        "action": "TALK",
        "time": "12:28:42",
        "time_int": 44922,
        "user": "zjrenju92",
        "content": "哦"
    },
    {
        "action": "MOVE",
        "time": "12:28:48",
        "time_int": 44928,
        "user": "GrandMaster",
        "content": "98"
    },
    {
        "action": "TALK",
        "time": "12:29:06",
        "time_int": 44946,
        "user": "GrandMaster",
        "content": "这个谁来摆一下吧？当复习"
    },
    {
        "action": "TALK",
        "time": "12:29:11",
        "time_int": 44951,
        "user": "zjrenju12",
        "content": "我"
    },
    {
        "action": "TALK",
        "time": "12:29:33",
        "time_int": 44973,
        "user": "zjrenju12",
        "content": "我忘记了"
    },
    {
        "action": "TALK",
        "time": "12:29:41",
        "time_int": 44981,
        "user": "GrandMaster",
        "content": "12？"
    },
    {
        "action": "MOVE",
        "time": "12:29:47",
        "time_int": 44987,
        "user": "zjrenju12",
        "content": "b6"
    },
    {
        "action": "TALK",
        "time": "12:29:58",
        "time_int": 44998,
        "user": "zjrenju12",
        "content": "？？"
    },
    {
        "action": "TALK",
        "time": "12:30:00",
        "time_int": 45000,
        "user": "zjrenju50",
        "content": "."
    },
    {
        "action": "BACK",
        "time": "12:30:03",
        "time_int": 45003,
        "user": "zjrenju12",
        "content": ""
    },
    {
        "action": "MOVE",
        "time": "12:30:07",
        "time_int": 45007,
        "user": "zjrenju12",
        "content": "b6"
    },
    {
        "action": "TALK",
        "time": "12:30:14",
        "time_int": 45014,
        "user": "zjrenju92",
        "content": "好棋！"
    },
    {
        "action": "MOVE",
        "time": "12:30:18",
        "time_int": 45018,
        "user": "GrandMaster",
        "content": "86"
    },
    {
        "action": "MOVE",
        "time": "12:30:39",
        "time_int": 45039,
        "user": "zjrenju12",
        "content": "a5"
    },
    {
        "action": "TALK",
        "time": "12:30:59",
        "time_int": 45059,
        "user": "GrandMaster",
        "content": "由于前面摆的那个杀。。所以说。。如果白20想防在右边那么必须把g6冲了。"
    },
    {
        "action": "TALK",
        "time": "12:31:01",
        "time_int": 45061,
        "user": "zjrenju12",
        "content": "错了吧"
    },
    {
        "action": "TALK",
        "time": "12:31:36",
        "time_int": 45096,
        "user": "GrandMaster",
        "content": "但是冲了g6黑多了f5之后将来黑活l7时白还是得跟m8那么下面还是多了一套f5，g4，h3的杀"
    },
    {
        "action": "TALK",
        "time": "12:31:42",
        "time_int": 45102,
        "user": "GrandMaster",
        "content": "所以说这个20是唯一"
    },
    {
        "action": "TALK",
        "time": "12:31:47",
        "time_int": 45107,
        "user": "GrandMaster",
        "content": "理解吗？"
    },
    {
        "action": "TALK",
        "time": "12:31:52",
        "time_int": 45112,
        "user": "zjrenju12",
        "content": "理解"
    },
    {
        "action": "MOVE",
        "time": "12:31:59",
        "time_int": 45119,
        "user": "GrandMaster",
        "content": "a4"
    },
    {
        "action": "TALK",
        "time": "12:32:10",
        "time_int": 45130,
        "user": "zjrenju12",
        "content": "明白了"
    },
    {
        "action": "TALK",
        "time": "12:32:25",
        "time_int": 45145,
        "user": "zjrenju92",
        "content": "理解"
    },
    {
        "action": "TALK",
        "time": "12:32:35",
        "time_int": 45155,
        "user": "GrandMaster",
        "content": "12好好想想现在该怎么杀哈"
    },
    {
        "action": "TALK",
        "time": "12:32:42",
        "time_int": 45162,
        "user": "zjrenju12",
        "content": "好的"
    },
    {
        "action": "TALK",
        "time": "12:32:47",
        "time_int": 45167,
        "user": "GrandMaster",
        "content": "和前面的杀有思路上的联系或者说是借用"
    },
    {
        "action": "TALK",
        "time": "12:33:14",
        "time_int": 45194,
        "user": "GrandMaster",
        "content": "但是杀是不一样了。"
    },
    {
        "action": "TALK",
        "time": "12:33:28",
        "time_int": 45208,
        "user": "zjrenju92",
        "content": "一样吧！"
    },
    {
        "action": "MOVE",
        "time": "12:33:33",
        "time_int": 45213,
        "user": "zjrenju12",
        "content": "c7"
    },
    {
        "action": "TALK",
        "time": "12:33:44",
        "time_int": 45224,
        "user": "zjrenju12",
        "content": "不一样"
    },
    {
        "action": "TALK",
        "time": "12:33:47",
        "time_int": 45227,
        "user": "GrandMaster",
        "content": "现在白m8唯一"
    },
    {
        "action": "MOVE",
        "time": "12:33:49",
        "time_int": 45229,
        "user": "GrandMaster",
        "content": "d8"
    },
    {
        "action": "TALK",
        "time": "12:33:57",
        "time_int": 45237,
        "user": "zjrenju92",
        "content": "对，20在右面是一样的。。"
    },
    {
        "action": "MOVE",
        "time": "12:34:49",
        "time_int": 45289,
        "user": "zjrenju12",
        "content": "c5"
    },
    {
        "action": "TALK",
        "time": "12:35:40",
        "time_int": 45340,
        "user": "GrandMaster",
        "content": "l5是手不错的棋"
    },
    {
        "action": "TALK",
        "time": "12:35:55",
        "time_int": 45355,
        "user": "GrandMaster",
        "content": "现在白不能活三防"
    },
    {
        "action": "TALK",
        "time": "12:36:10",
        "time_int": 45370,
        "user": "zjrenju12",
        "content": "不过好像杀不了"
    },
    {
        "action": "TALK",
        "time": "12:36:25",
        "time_int": 45385,
        "user": "zjrenju92",
        "content": "恩"
    },
    {
        "action": "TALK",
        "time": "12:36:29",
        "time_int": 45389,
        "user": "zjrenju88",
        "content": "G7"
    },
    {
        "action": "TALK",
        "time": "12:36:35",
        "time_int": 45395,
        "user": "GrandMaster",
        "content": "g7？"
    },
    {
        "action": "TALK",
        "time": "12:36:38",
        "time_int": 45398,
        "user": "zjrenju12",
        "content": "可以杀"
    },
    {
        "action": "TALK",
        "time": "12:36:47",
        "time_int": 45407,
        "user": "GrandMaster",
        "content": "黑右边m6，n5，m4，m5是vcf"
    },
    {
        "action": "TALK",
        "time": "12:36:58",
        "time_int": 45418,
        "user": "GrandMaster",
        "content": "所以我说现在白不能活三来防"
    },
    {
        "action": "TALK",
        "time": "12:37:06",
        "time_int": 45426,
        "user": "zjrenju12",
        "content": "左边也可以吧"
    },
    {
        "action": "TALK",
        "time": "12:37:55",
        "time_int": 45475,
        "user": "zjrenju92",
        "content": "右 边应该可以杀吧！"
    },
    {
        "action": "TALK",
        "time": "12:37:58",
        "time_int": 45478,
        "user": "GrandMaster",
        "content": "大家说防哪"
    },
    {
        "action": "TALK",
        "time": "12:38:03",
        "time_int": 45483,
        "user": "zjrenju12",
        "content": "右边可以"
    },
    {
        "action": "TALK",
        "time": "12:38:08",
        "time_int": 45488,
        "user": "zjrenju88",
        "content": "M6？"
    },
    {
        "action": "MOVE",
        "time": "12:38:39",
        "time_int": 45519,
        "user": "GrandMaster",
        "content": "d6"
    },
    {
        "action": "TALK",
        "time": "12:38:40",
        "time_int": 45520,
        "user": "zjrenju17",
        "content": "."
    },
    {
        "action": "TALK",
        "time": "12:38:44",
        "time_int": 45524,
        "user": "zjrenju92",
        "content": "L6"
    },
    {
        "action": "MOVE",
        "time": "12:39:06",
        "time_int": 45546,
        "user": "GrandMaster",
        "content": "c3"
    },
    {
        "action": "TALK",
        "time": "12:39:26",
        "time_int": 45566,
        "user": "GrandMaster",
        "content": "m6的话估计这样差不多黑就必胜 了吧"
    },
    {
        "action": "TALK",
        "time": "12:39:27",
        "time_int": 45567,
        "user": "zjrenju92",
        "content": "L6唯一！"
    },
    {
        "action": "TALK",
        "time": "12:40:02",
        "time_int": 45602,
        "user": "GrandMaster",
        "content": "m6看似防掉斜线。但是黑可以不利用那套斜线"
    },
    {
        "action": "TALK",
        "time": "12:40:14",
        "time_int": 45614,
        "user": "Guest863",
        "content": "28-M5"
    },
    {
        "action": "MOVE",
        "time": "12:40:25",
        "time_int": 45625,
        "user": "GrandMaster",
        "content": "d4"
    },
    {
        "action": "TALK",
        "time": "12:40:26",
        "time_int": 45626,
        "user": "Guest863",
        "content": "28-M4"
    },
    {
        "action": "BACK",
        "time": "12:40:29",
        "time_int": 45629,
        "user": "GrandMaster",
        "content": ""
    },
    {
        "action": "TALK",
        "time": "12:40:32",
        "time_int": 45632,
        "user": "zjrenju88",
        "content": "K3杀"
    },
    {
        "action": "TALK",
        "time": "12:40:36",
        "time_int": 45636,
        "user": "zjrenju88",
        "content": "每用"
    },
    {
        "action": "MOVE",
        "time": "12:40:42",
        "time_int": 45642,
        "user": "GrandMaster",
        "content": "d5"
    },
    {
        "action": "MOVE",
        "time": "12:40:46",
        "time_int": 45646,
        "user": "GrandMaster",
        "content": "85"
    },
    {
        "action": "MOVE",
        "time": "12:40:49",
        "time_int": 45649,
        "user": "GrandMaster",
        "content": "74"
    },
    {
        "action": "MOVE",
        "time": "12:40:52",
        "time_int": 45652,
        "user": "GrandMaster",
        "content": "b5"
    },
    {
        "action": "MOVE",
        "time": "12:40:57",
        "time_int": 45657,
        "user": "GrandMaster",
        "content": "95"
    },
    {
        "action": "TALK",
        "time": "12:41:02",
        "time_int": 45662,
        "user": "zjrenju92",
        "content": "VCF了"
    },
    {
        "action": "MOVE",
        "time": "12:41:11",
        "time_int": 45671,
        "user": "zjrenju12",
        "content": "c4"
    },
    {
        "action": "MOVE",
        "time": "12:41:16",
        "time_int": 45676,
        "user": "GrandMaster",
        "content": "c6"
    },
    {
        "action": "MOVE",
        "time": "12:41:20",
        "time_int": 45680,
        "user": "GrandMaster",
        "content": "d4"
    },
    {
        "action": "MOVE",
        "time": "12:41:24",
        "time_int": 45684,
        "user": "GrandMaster",
        "content": "e3"
    },
    {
        "action": "MOVE",
        "time": "12:41:31",
        "time_int": 45691,
        "user": "zjrenju12",
        "content": "d2"
    },
    {
        "action": "MOVE",
        "time": "12:41:38",
        "time_int": 45698,
        "user": "GrandMaster",
        "content": "b4"
    },
    {
        "action": "MOVE",
        "time": "12:41:40",
        "time_int": 45700,
        "user": "zjrenju12",
        "content": "e2"
    },
    {
        "action": "MOVE",
        "time": "12:41:42",
        "time_int": 45702,
        "user": "GrandMaster",
        "content": "d3"
    },
    {
        "action": "MOVE",
        "time": "12:41:45",
        "time_int": 45705,
        "user": "zjrenju12",
        "content": "c2"
    },
    {
        "action": "TALK",
        "time": "12:41:48",
        "time_int": 45708,
        "user": "GrandMaster",
        "content": "聪明哈"
    },
    {
        "action": "TALK",
        "time": "12:41:52",
        "time_int": 45712,
        "user": "GrandMaster",
        "content": "别的v都是假的"
    },
    {
        "action": "TALK",
        "time": "12:41:55",
        "time_int": 45715,
        "user": "zjrenju92",
        "content": "厉害！"
    },
    {
        "action": "TALK",
        "time": "12:42:11",
        "time_int": 45731,
        "user": "tommy",
        "content": "：）"
    },
    {
        "action": "TALK",
        "time": "12:42:13",
        "time_int": 45733,
        "user": "zjrenju06",
        "content": "ＧＭ好厉害哇～～～｀"
    },
    {
        "action": "TALK",
        "time": "12:42:14",
        "time_int": 45734,
        "user": "zjrenju12",
        "content": "老师那怎么防守"
    },
    {
        "action": "TALK",
        "time": "12:42:15",
        "time_int": 45735,
        "user": "dittp",
        "content": "不是吧"
    },
    {
        "action": "GOTO",
        "time": "12:42:20",
        "time_int": 45740,
        "user": "GrandMaster",
        "content": 25
    },
    {
        "action": "MOVE",
        "time": "12:42:24",
        "time_int": 45744,
        "user": "GrandMaster",
        "content": "c6"
    },
    {
        "action": "TALK",
        "time": "12:42:33",
        "time_int": 45753,
        "user": "zjrenju50",
        "content": "84"
    },
    {
        "action": "TALK",
        "time": "12:43:03",
        "time_int": 45783,
        "user": "zjrenju92",
        "content": "这个26 黑估计很难`杀"
    },
    {
        "action": "TALK",
        "time": "12:43:29",
        "time_int": 45809,
        "user": "GrandMaster",
        "content": "这样大家觉得还有杀吗"
    },
    {
        "action": "TALK",
        "time": "12:43:50",
        "time_int": 45830,
        "user": "zjrenju06",
        "content": "不知道耶～～～嘿嘿"
    },
    {
        "action": "TALK",
        "time": "12:43:52",
        "time_int": 45832,
        "user": "zjrenju88",
        "content": "J3？"
    },
    {
        "action": "TALK",
        "time": "12:43:52",
        "time_int": 45832,
        "user": "zjrenju92",
        "content": "没了"
    },
    {
        "action": "TALK",
        "time": "12:44:27",
        "time_int": 45867,
        "user": "zjrenju12",
        "content": "又"
    },
    {
        "action": "TALK",
        "time": "12:44:34",
        "time_int": 45874,
        "user": "zjrenju12",
        "content": "有的"
    },
    {
        "action": "MOVE",
        "time": "12:44:40",
        "time_int": 45880,
        "user": "GrandMaster",
        "content": "a3"
    },
    {
        "action": "MOVE",
        "time": "12:44:55",
        "time_int": 45895,
        "user": "GrandMaster",
        "content": "65"
    },
    {
        "action": "MOVE",
        "time": "12:44:59",
        "time_int": 45899,
        "user": "GrandMaster",
        "content": "76"
    },
    {
        "action": "MOVE",
        "time": "12:45:28",
        "time_int": 45928,
        "user": "GrandMaster",
        "content": "b5"
    },
    {
        "action": "TALK",
        "time": "12:45:47",
        "time_int": 45947,
        "user": "Guest863",
        "content": "I4"
    },
    {
        "action": "TALK",
        "time": "12:45:50",
        "time_int": 45950,
        "user": "Guest863",
        "content": ":))"
    },
    {
        "action": "TALK",
        "time": "12:46:05",
        "time_int": 45965,
        "user": "GrandMaster",
        "content": "可惜黑是四四啊"
    },
    {
        "action": "TALK",
        "time": "12:46:26",
        "time_int": 45986,
        "user": "zjrenju12",
        "content": "老师27 不这么走可以吗？"
    },
    {
        "action": "TALK",
        "time": "12:46:37",
        "time_int": 45997,
        "user": "zjrenju88",
        "content": "I3"
    },
    {
        "action": "TALK",
        "time": "12:46:41",
        "time_int": 46001,
        "user": "zjrenju13",
        "content": ".."
    },
    {
        "action": "TALK",
        "time": "12:46:46",
        "time_int": 46006,
        "user": "GrandMaster",
        "content": "12你说走哪呢"
    },
    {
        "action": "TALK",
        "time": "12:46:57",
        "time_int": 46017,
        "user": "zjrenju12",
        "content": "冲4"
    },
    {
        "action": "MOVE",
        "time": "12:47:06",
        "time_int": 46026,
        "user": "GrandMaster",
        "content": "93"
    },
    {
        "action": "TALK",
        "time": "12:47:07",
        "time_int": 46027,
        "user": "zjrenju92",
        "content": "这个27挺厉害，好象防不住，左右都杀啊！"
    },
    {
        "action": "MOVE",
        "time": "12:47:17",
        "time_int": 46037,
        "user": "GrandMaster",
        "content": "b3"
    },
    {
        "action": "MOVE",
        "time": "12:47:23",
        "time_int": 46043,
        "user": "GrandMaster",
        "content": "95"
    },
    {
        "action": "MOVE",
        "time": "12:47:43",
        "time_int": 46063,
        "user": "GrandMaster",
        "content": "94"
    },
    {
        "action": "TALK",
        "time": "12:48:06",
        "time_int": 46086,
        "user": "GrandMaster",
        "content": "差不多这样黑就没杀了吧"
    },
    {
        "action": "TALK",
        "time": "12:48:11",
        "time_int": 46091,
        "user": "zjrenju92",
        "content": "其实33已经VCF了。。。。"
    },
    {
        "action": "TALK",
        "time": "12:48:38",
        "time_int": 46118,
        "user": "zjrenju88",
        "content": "是呀GM"
    },
    {
        "action": "TALK",
        "time": "12:48:42",
        "time_int": 46122,
        "user": "GrandMaster",
        "content": "恩。对"
    },
    {
        "action": "BACK",
        "time": "12:48:43",
        "time_int": 46123,
        "user": "GrandMaster",
        "content": ""
    },
    {
        "action": "BACK",
        "time": "12:48:44",
        "time_int": 46124,
        "user": "GrandMaster",
        "content": ""
    },
    {
        "action": "TALK",
        "time": "12:48:46",
        "time_int": 46126,
        "user": "zjrenju88",
        "content": "不用防"
    },
    {
        "action": "BACK",
        "time": "12:48:47",
        "time_int": 46127,
        "user": "GrandMaster",
        "content": ""
    },
    {
        "action": "TALK",
        "time": "12:48:50",
        "time_int": 46130,
        "user": "zjrenju92",
        "content": "G4，H3，G3"
    },
    {
        "action": "BACK",
        "time": "12:48:51",
        "time_int": 46131,
        "user": "GrandMaster",
        "content": ""
    },
    {
        "action": "TALK",
        "time": "12:48:55",
        "time_int": 46135,
        "user": "wzqclass08",
        "content": "今天是谁上课？"
    },
    {
        "action": "BACK",
        "time": "12:48:55",
        "time_int": 46135,
        "user": "GrandMaster",
        "content": ""
    },
    {
        "action": "MOVE",
        "time": "12:49:04",
        "time_int": 46144,
        "user": "GrandMaster",
        "content": "b3"
    },
    {
        "action": "TALK",
        "time": "12:49:08",
        "time_int": 46148,
        "user": "zjrenju12",
        "content": "老师27直接杀可以吗？"
    },
    {
        "action": "TALK",
        "time": "12:49:12",
        "time_int": 46152,
        "user": "GrandMaster",
        "content": "这里错了个次序"
    },
    {
        "action": "TALK",
        "time": "12:49:23",
        "time_int": 46163,
        "user": "zjrenju88",
        "content": "还是V"
    },
    {
        "action": "TALK",
        "time": "12:49:33",
        "time_int": 46173,
        "user": "GrandMaster",
        "content": "你说怎么v呀"
    },
    {
        "action": "TALK",
        "time": "12:49:37",
        "time_int": 46177,
        "user": "zjrenju88",
        "content": "H5"
    },
    {
        "action": "TALK",
        "time": "12:49:40",
        "time_int": 46180,
        "user": "zjrenju88",
        "content": "I5"
    },
    {
        "action": "TALK",
        "time": "12:49:59",
        "time_int": 46199,
        "user": "GrandMaster",
        "content": "继续"
    },
    {
        "action": "TALK",
        "time": "12:50:38",
        "time_int": 46238,
        "user": "zjrenju88",
        "content": "不行"
    },
    {
        "action": "TALK",
        "time": "12:50:43",
        "time_int": 46243,
        "user": "GrandMaster",
        "content": "i4是四四"
    },
    {
        "action": "TALK",
        "time": "12:50:45",
        "time_int": 46245,
        "user": "GrandMaster",
        "content": "所以冲不到了。"
    },
    {
        "action": "TALK",
        "time": "12:50:46",
        "time_int": 46246,
        "user": "dittp",
        "content": "KLM?"
    },
    {
        "action": "TALK",
        "time": "12:50:47",
        "time_int": 46247,
        "user": "GrandMaster",
        "content": "对吗"
    },
    {
        "action": "TALK",
        "time": "12:50:57",
        "time_int": 46257,
        "user": "zjrenju92",
        "content": "恩"
    },
    {
        "action": "TALK",
        "time": "12:51:00",
        "time_int": 46260,
        "user": "zjrenju88",
        "content": "这里I5"
    },
    {
        "action": "TALK",
        "time": "12:51:00",
        "time_int": 46260,
        "user": "wzqclass08",
        "content": "GrandMaster是谁？"
    },
    {
        "action": "TALK",
        "time": "12:51:12",
        "time_int": 46272,
        "user": "zjrenju06",
        "content": "保密，不告诉你耶～～～｀"
    },
    {
        "action": "TALK",
        "time": "12:51:14",
        "time_int": 46274,
        "user": "GrandMaster",
        "content": "所以现在就只能i5了"
    },
    {
        "action": "MOVE",
        "time": "12:51:16",
        "time_int": 46276,
        "user": "GrandMaster",
        "content": "95"
    },
    {
        "action": "MOVE",
        "time": "12:51:19",
        "time_int": 46279,
        "user": "GrandMaster",
        "content": "b5"
    },
    {
        "action": "TALK",
        "time": "12:51:27",
        "time_int": 46287,
        "user": "wzqclass08",
        "content": "浙江的？"
    },
    {
        "action": "TALK",
        "time": "12:51:27",
        "time_int": 46287,
        "user": "tommy",
        "content": "没有点名吧，我刚死机了"
    },
    {
        "action": "TALK",
        "time": "12:51:37",
        "time_int": 46297,
        "user": "GrandMaster",
        "content": "这样的次序黑就不能有v了。"
    },
    {
        "action": "TALK",
        "time": "12:51:39",
        "time_int": 46299,
        "user": "zjrenju06",
        "content": "不知道耶～～～｀好好听课吧，乖"
    },
    {
        "action": "TALK",
        "time": "12:51:50",
        "time_int": 46310,
        "user": "wzqclass08",
        "content": "。。"
    },
    {
        "action": "TALK",
        "time": "12:51:59",
        "time_int": 46319,
        "user": "zjrenju88",
        "content": "I3"
    },
    {
        "action": "MOVE",
        "time": "12:52:03",
        "time_int": 46323,
        "user": "GrandMaster",
        "content": "93"
    },
    {
        "action": "MOVE",
        "time": "12:52:06",
        "time_int": 46326,
        "user": "GrandMaster",
        "content": "94"
    },
    {
        "action": "TALK",
        "time": "12:52:17",
        "time_int": 46337,
        "user": "wzqclass08",
        "content": "dittp是顾老师吗？"
    },
    {
        "action": "TALK",
        "time": "12:52:17",
        "time_int": 46337,
        "user": "zjrenju88",
        "content": "恩"
    },
    {
        "action": "TALK",
        "time": "12:52:25",
        "time_int": 46345,
        "user": "zjrenju88",
        "content": "这样没了"
    },
    {
        "action": "CHECKRESULT",
        "time": "12:52:27",
        "time_int": 46347,
        "user": "",
        "content": " weigui, zjrenju51, zjrenju88, zjrenju50, zjrenju06, zjrenju99, zjrenju92, wzqclass08, tommy, zjrenju18, zjrenju12, dittp, zjrenju17, zjrenju13."
    },
    {
        "action": "TALK",
        "time": "12:52:33",
        "time_int": 46353,
        "user": "zjrenju88",
        "content": "27臭"
    },
    {
        "action": "TALK",
        "time": "12:53:01",
        "time_int": 46381,
        "user": "zjrenju92",
        "content": "27太香了！"
    },
    {
        "action": "TALK",
        "time": "12:53:08",
        "time_int": 46388,
        "user": "zjrenju88",
        "content": "。。。"
    },
    {
        "action": "TALK",
        "time": "12:53:12",
        "time_int": 46392,
        "user": "GrandMaster",
        "content": "这样就没杀了。"
    },
    {
        "action": "TALK",
        "time": "12:53:16",
        "time_int": 46396,
        "user": "dittp",
        "content": "不是"
    },
    {
        "action": "TALK",
        "time": "12:53:20",
        "time_int": 46400,
        "user": "zjrenju88",
        "content": "还是不会算：（"
    },
    {
        "action": "TALK",
        "time": "12:53:22",
        "time_int": 46402,
        "user": "zjrenju88",
        "content": "5555555"
    },
    {
        "action": "TALK",
        "time": "12:53:23",
        "time_int": 46403,
        "user": "wzqclass08",
        "content": "那是who?"
    },
    {
        "action": "TALK",
        "time": "12:53:31",
        "time_int": 46411,
        "user": "zjrenju92",
        "content": "31走G7呢？"
    },
    {
        "action": "TALK",
        "time": "12:53:36",
        "time_int": 46416,
        "user": "dittp",
        "content": "是俺"
    },
    {
        "action": "BACK",
        "time": "12:53:44",
        "time_int": 46424,
        "user": "GrandMaster",
        "content": ""
    },
    {
        "action": "BACK",
        "time": "12:53:44",
        "time_int": 46424,
        "user": "GrandMaster",
        "content": ""
    },
    {
        "action": "TALK",
        "time": "12:53:44",
        "time_int": 46424,
        "user": "wzqclass08",
        "content": "你是谁呀？"
    },
    {
        "action": "BACK",
        "time": "12:53:47",
        "time_int": 46427,
        "user": "GrandMaster",
        "content": ""
    },
    {
        "action": "BACK",
        "time": "12:53:47",
        "time_int": 46427,
        "user": "GrandMaster",
        "content": ""
    },
    {
        "action": "BACK",
        "time": "12:53:47",
        "time_int": 46427,
        "user": "GrandMaster",
        "content": ""
    },
    {
        "action": "BACK",
        "time": "12:53:50",
        "time_int": 46430,
        "user": "GrandMaster",
        "content": ""
    },
    {
        "action": "MOVE",
        "time": "12:53:51",
        "time_int": 46431,
        "user": "GrandMaster",
        "content": "76"
    },
    {
        "action": "MOVE",
        "time": "12:53:54",
        "time_int": 46434,
        "user": "GrandMaster",
        "content": "b3"
    },
    {
        "action": "MOVE",
        "time": "12:53:57",
        "time_int": 46437,
        "user": "GrandMaster",
        "content": "77"
    },
    {
        "action": "TALK",
        "time": "12:54:39",
        "time_int": 46479,
        "user": "zjrenju99",
        "content": "CLASS08你是谁呀?"
    },
    {
        "action": "MOVE",
        "time": "12:54:50",
        "time_int": 46490,
        "user": "GrandMaster",
        "content": "75"
    },
    {
        "action": "TALK",
        "time": "12:55:02",
        "time_int": 46502,
        "user": "wzqclass08",
        "content": "今天是浙江连珠的课？"
    },
    {
        "action": "TALK",
        "time": "12:55:11",
        "time_int": 46511,
        "user": "zjrenju99",
        "content": "YES"
    },
    {
        "action": "TALK",
        "time": "12:55:20",
        "time_int": 46520,
        "user": "wzqclass08",
        "content": "录象有下载吗？"
    },
    {
        "action": "TALK",
        "time": "12:55:23",
        "time_int": 46523,
        "user": "zjrenju99",
        "content": "难道是你的课?"
    },
    {
        "action": "TALK",
        "time": "12:55:29",
        "time_int": 46529,
        "user": "zjrenju99",
        "content": "没分没的下载"
    },
    {
        "action": "TALK",
        "time": "12:55:31",
        "time_int": 46531,
        "user": "wzqclass08",
        "content": "给我个连接"
    },
    {
        "action": "TALK",
        "time": "12:55:36",
        "time_int": 46536,
        "user": "zjrenju92",
        "content": "08 是chess这么出名的人都不认识？"
    },
    {
        "action": "TALK",
        "time": "12:55:36",
        "time_int": 46536,
        "user": "tommy",
        "content": "h5??"
    },
    {
        "action": "MOVE",
        "time": "12:55:45",
        "time_int": 46545,
        "user": "GrandMaster",
        "content": "95"
    },
    {
        "action": "MOVE",
        "time": "12:55:49",
        "time_int": 46549,
        "user": "GrandMaster",
        "content": "b5"
    },
    {
        "action": "TALK",
        "time": "12:55:50",
        "time_int": 46550,
        "user": "wzqclass08",
        "content": "。。。"
    },
    {
        "action": "TALK",
        "time": "12:55:50",
        "time_int": 46550,
        "user": "zjrenju99",
        "content": "出名就要认识啊"
    },
    {
        "action": "TALK",
        "time": "12:55:54",
        "time_int": 46554,
        "user": "zjrenju99",
        "content": "我偏不认识"
    },
    {
        "action": "TALK",
        "time": "12:55:56",
        "time_int": 46556,
        "user": "GrandMaster",
        "content": "这样基本就还原了。"
    },
    {
        "action": "TALK",
        "time": "12:56:03",
        "time_int": 46563,
        "user": "zjrenju92",
        "content": "恩"
    },
    {
        "action": "GOTO",
        "time": "12:56:11",
        "time_int": 46571,
        "user": "GrandMaster",
        "content": 24
    },
    {
        "action": "TALK",
        "time": "12:56:12",
        "time_int": 46572,
        "user": "zjrenju88",
        "content": "大哥们，上课呢哈"
    },
    {
        "action": "TALK",
        "time": "12:56:28",
        "time_int": 46588,
        "user": "zjrenju99",
        "content": "你才大哥"
    },
    {
        "action": "TALK",
        "time": "12:56:33",
        "time_int": 46593,
        "user": "zjrenju99",
        "content": "叫我大姐"
    },
    {
        "action": "TALK",
        "time": "12:56:47",
        "time_int": 46607,
        "user": "zjrenju50",
        "content": "请叫我阿姨"
    },
    {
        "action": "TALK",
        "time": "12:56:50",
        "time_int": 46610,
        "user": "zjrenju12",
        "content": "还是个千金大姐"
    },
    {
        "action": "TALK",
        "time": "12:56:57",
        "time_int": 46617,
        "user": "zjrenju60",
        "content": "奶奶们好"
    },
    {
        "action": "TALK",
        "time": "12:57:08",
        "time_int": 46628,
        "user": "zjrenju12",
        "content": "\/puke"
    },
    {
        "action": "TALK",
        "time": "12:57:13",
        "time_int": 46633,
        "user": "zjrenju06",
        "content": "哈哈哈。。"
    },
    {
        "action": "TALK",
        "time": "12:57:15",
        "time_int": 46635,
        "user": "zjrenju99",
        "content": "乖~~~孙子好"
    },
    {
        "action": "TALK",
        "time": "12:57:21",
        "time_int": 46641,
        "user": "zjrenju12",
        "content": "老师"
    },
    {
        "action": "TALK",
        "time": "12:57:26",
        "time_int": 46646,
        "user": "GrandMaster",
        "content": "这里25的做棋点要选择的和左边的联系好一点"
    },
    {
        "action": "TALK",
        "time": "12:57:27",
        "time_int": 46647,
        "user": "zjrenju60",
        "content": "99岁的老祖母好"
    },
    {
        "action": "TALK",
        "time": "12:57:38",
        "time_int": 46658,
        "user": "zjrenju99",
        "content": "恩乖~~~曾孙子好"
    },
    {
        "action": "TALK",
        "time": "12:57:52",
        "time_int": 46672,
        "user": "zjrenju12",
        "content": "刚才的27不那么走是不是可以杀"
    },
    {
        "action": "TALK",
        "time": "12:57:54",
        "time_int": 46674,
        "user": "zjrenju06",
        "content": "那２５应该下哪儿呢"
    },
    {
        "action": "MOVE",
        "time": "12:58:00",
        "time_int": 46680,
        "user": "GrandMaster",
        "content": "c3"
    },
    {
        "action": "TALK",
        "time": "12:58:03",
        "time_int": 46683,
        "user": "zjrenju60",
        "content": "老祖母您眼花啦"
    },
    {
        "action": "TALK",
        "time": "12:58:09",
        "time_int": 46689,
        "user": "zjrenju60",
        "content": "我是女的"
    },
    {
        "action": "TALK",
        "time": "12:58:13",
        "time_int": 46693,
        "user": "wzqclass08",
        "content": "浙江的连珠教室谁能把网址给我？"
    },
    {
        "action": "TALK",
        "time": "12:58:24",
        "time_int": 46704,
        "user": "zjrenju99",
        "content": "恩~~那换增孙女好了!我不介意你换性别的"
    },
    {
        "action": "TALK",
        "time": "12:58:51",
        "time_int": 46731,
        "user": "tommy",
        "content": "瞧瞧，把GM吓跑了"
    },
    {
        "action": "TALK",
        "time": "12:58:53",
        "time_int": 46733,
        "user": "wzqclass08",
        "content": "92，你是谁？"
    },
    {
        "action": "TALK",
        "time": "12:58:54",
        "time_int": 46734,
        "user": "zjrenju99",
        "content": "就当我老眼昏花~~~没办法世界观不同嘛"
    },
    {
        "action": "TALK",
        "time": "12:58:55",
        "time_int": 46735,
        "user": "Guest863",
        "content": "GGGGGGGGG                    M"
    },
    {
        "action": "TALK",
        "time": "12:59:26",
        "time_int": 46766,
        "user": "zjrenju50",
        "content": "www.zjrenju.net"
    },
    {
        "action": "TALK",
        "time": "12:59:33",
        "time_int": 46773,
        "user": "wzqclass08",
        "content": "谢谢"
    },
    {
        "action": "TALK",
        "time": "12:59:36",
        "time_int": 46776,
        "user": "zjrenju92",
        "content": "92 是 XUWU"
    },
    {
        "action": "TALK",
        "time": "13:00:03",
        "time_int": 46803,
        "user": "zjrenju60",
        "content": "4242，您老不死的该如土啦"
    },
    {
        "action": "TALK",
        "time": "13:00:13",
        "time_int": 46813,
        "user": "zjrenju12",
        "content": "大家好好听课好吗？"
    },
    {
        "action": "TALK",
        "time": "13:00:21",
        "time_int": 46821,
        "user": "zjrenju99",
        "content": "哎~~比我还会打错别字,谁昏花啦"
    },
    {
        "action": "TALK",
        "time": "13:00:23",
        "time_int": 46823,
        "user": "Guest863",
        "content": "别吵了"
    },
    {
        "action": "TALK",
        "time": "13:00:41",
        "time_int": 46841,
        "user": "zjrenju99",
        "content": "好啦~~我不计较了"
    },
    {
        "action": "TALK",
        "time": "13:00:45",
        "time_int": 46845,
        "user": "zjrenju99",
        "content": "不说了"
    },
    {
        "action": "TALK",
        "time": "13:00:46",
        "time_int": 46846,
        "user": "zjrenju12",
        "content": "老师k2可以吗？"
    },
    {
        "action": "TALK",
        "time": "13:00:50",
        "time_int": 46850,
        "user": "zjrenju92",
        "content": "这个25好，和左边连接了！"
    },
    {
        "action": "TALK",
        "time": "13:01:08",
        "time_int": 46868,
        "user": "zjrenju88",
        "content": "没的防了好象"
    },
    {
        "action": "TALK",
        "time": "13:01:15",
        "time_int": 46875,
        "user": "wzqclass08",
        "content": "虚无？"
    },
    {
        "action": "TALK",
        "time": "13:01:16",
        "time_int": 46876,
        "user": "zjrenju60",
        "content": "如土就是和土一样了，老祖母世界观太落后啦"
    },
    {
        "action": "TALK",
        "time": "13:01:35",
        "time_int": 46895,
        "user": "zjrenju60",
        "content": "尸体变成泥土就是如土了"
    },
    {
        "action": "TALK",
        "time": "13:01:39",
        "time_int": 46899,
        "user": "GrandMaster",
        "content": "60，都说停了。你也stop。。ok？"
    },
    {
        "action": "TALK",
        "time": "13:01:45",
        "time_int": 46905,
        "user": "zjrenju92",
        "content": "60,shut up!"
    },
    {
        "action": "TALK",
        "time": "13:01:48",
        "time_int": 46908,
        "user": "zjrenju99",
        "content": "....今天牛奶蛮好喝的"
    },
    {
        "action": "TALK",
        "time": "13:02:08",
        "time_int": 46928,
        "user": "zjrenju99",
        "content": "^-^"
    },
    {
        "action": "TALK",
        "time": "13:02:12",
        "time_int": 46932,
        "user": "zjrenju99",
        "content": "^_^"
    },
    {
        "action": "TALK",
        "time": "13:02:13",
        "time_int": 46933,
        "user": "zjrenju88",
        "content": "有V又有双杀"
    },
    {
        "action": "MOVE",
        "time": "13:02:18",
        "time_int": 46938,
        "user": "GrandMaster",
        "content": "b2"
    },
    {
        "action": "TALK",
        "time": "13:02:25",
        "time_int": 46945,
        "user": "zjrenju50",
        "content": "没看出来~：（"
    },
    {
        "action": "TALK",
        "time": "13:02:26",
        "time_int": 46946,
        "user": "zjrenju60",
        "content": "不好玩了～～～"
    },
    {
        "action": "TALK",
        "time": "13:02:28",
        "time_int": 46948,
        "user": "GrandMaster",
        "content": "那么我们来看看k2这个防点"
    },
    {
        "action": "TALK",
        "time": "13:02:43",
        "time_int": 46963,
        "user": "zjrenju88",
        "content": "M6？"
    },
    {
        "action": "TALK",
        "time": "13:02:52",
        "time_int": 46972,
        "user": "GrandMaster",
        "content": "大家看一下。怎么杀"
    },
    {
        "action": "TALK",
        "time": "13:03:04",
        "time_int": 46984,
        "user": "zjrenju88",
        "content": "H5"
    },
    {
        "action": "TALK",
        "time": "13:03:14",
        "time_int": 46994,
        "user": "zjrenju50",
        "content": "阿拉法特政治遗嘱？"
    },
    {
        "action": "TALK",
        "time": "13:03:37",
        "time_int": 47017,
        "user": "zjrenju92",
        "content": "L5做杀"
    },
    {
        "action": "TALK",
        "time": "13:03:54",
        "time_int": 47034,
        "user": "GrandMaster",
        "content": "谁愿意来试下吗"
    },
    {
        "action": "TALK",
        "time": "13:03:59",
        "time_int": 47039,
        "user": "zjrenju99",
        "content": "我~~~~"
    },
    {
        "action": "TALK",
        "time": "13:03:59",
        "time_int": 47039,
        "user": "zjrenju92",
        "content": "我"
    },
    {
        "action": "MOVE",
        "time": "13:04:25",
        "time_int": 47065,
        "user": "zjrenju92",
        "content": "c5"
    },
    {
        "action": "TALK",
        "time": "13:05:08",
        "time_int": 47108,
        "user": "GrandMaster",
        "content": "恩。虽然自己做四四。不过l5这个联系还是很好"
    },
    {
        "action": "TALK",
        "time": "13:05:45",
        "time_int": 47145,
        "user": "GrandMaster",
        "content": "这样就防不住了。"
    },
    {
        "action": "TALK",
        "time": "13:05:47",
        "time_int": 47147,
        "user": "GrandMaster",
        "content": "vcf太多了。"
    },
    {
        "action": "TALK",
        "time": "13:05:59",
        "time_int": 47159,
        "user": "zjrenju92",
        "content": "是的"
    },
    {
        "action": "TALK",
        "time": "13:06:00",
        "time_int": 47160,
        "user": "GrandMaster",
        "content": "大家稍微看一下吧"
    },
    {
        "action": "TALK",
        "time": "13:06:52",
        "time_int": 47212,
        "user": "GrandMaster",
        "content": "没有疑问吧"
    },
    {
        "action": "TALK",
        "time": "13:06:54",
        "time_int": 47214,
        "user": "GrandMaster",
        "content": "这里"
    },
    {
        "action": "TALK",
        "time": "13:07:00",
        "time_int": 47220,
        "user": "tommy",
        "content": "嗯"
    },
    {
        "action": "TALK",
        "time": "13:07:05",
        "time_int": 47225,
        "user": "zjrenju50",
        "content": "没"
    },
    {
        "action": "TALK",
        "time": "13:07:15",
        "time_int": 47235,
        "user": "zjrenju88",
        "content": "M2"
    },
    {
        "action": "TALK",
        "time": "13:07:31",
        "time_int": 47251,
        "user": "GrandMaster",
        "content": "k4，m6这两个点的vcf还有m5，m6，m4的两套v只有防m6点"
    },
    {
        "action": "TALK",
        "time": "13:07:34",
        "time_int": 47254,
        "user": "zjrenju12",
        "content": "不行"
    },
    {
        "action": "TALK",
        "time": "13:07:49",
        "time_int": 47269,
        "user": "zjrenju12",
        "content": "怎么都杀了"
    },
    {
        "action": "TALK",
        "time": "13:07:50",
        "time_int": 47270,
        "user": "GrandMaster",
        "content": "但是防完m6后vm3，n3又是一套vcf"
    },
    {
        "action": "TALK",
        "time": "13:07:52",
        "time_int": 47272,
        "user": "zjrenju92",
        "content": "防哪也不行了"
    },
    {
        "action": "TALK",
        "time": "13:08:00",
        "time_int": 47280,
        "user": "GrandMaster",
        "content": "m2也是m3，n3vcf"
    },
    {
        "action": "TALK",
        "time": "13:08:21",
        "time_int": 47301,
        "user": "zjrenju88",
        "content": "：）"
    },
    {
        "action": "TALK",
        "time": "13:08:26",
        "time_int": 47306,
        "user": "GrandMaster",
        "content": "88看到了吗"
    },
    {
        "action": "TALK",
        "time": "13:08:41",
        "time_int": 47321,
        "user": "zjrenju88",
        "content": "恩"
    },
    {
        "action": "TALK",
        "time": "13:08:46",
        "time_int": 47326,
        "user": "zjrenju51",
        "content": "meile"
    },
    {
        "action": "TALK",
        "time": "13:08:56",
        "time_int": 47336,
        "user": "zjrenju50",
        "content": "51许梦婷？"
    },
    {
        "action": "TALK",
        "time": "13:09:59",
        "time_int": 47399,
        "user": "GrandMaster",
        "content": "所以这里就没防了。"
    },
    {
        "action": "TALK",
        "time": "13:10:00",
        "time_int": 47400,
        "user": "weigui",
        "content": "不是，是临时用的"
    },
    {
        "action": "TALK",
        "time": "13:10:08",
        "time_int": 47408,
        "user": "zjrenju50",
        "content": "O"
    },
    {
        "action": "GOTO",
        "time": "13:10:58",
        "time_int": 47458,
        "user": "GrandMaster",
        "content": 25
    },
    {
        "action": "TALK",
        "time": "13:11:10",
        "time_int": 47470,
        "user": "GrandMaster",
        "content": "再来看看别的26"
    },
    {
        "action": "MOVE",
        "time": "13:12:00",
        "time_int": 47520,
        "user": "GrandMaster",
        "content": "c6"
    },
    {
        "action": "TALK",
        "time": "13:12:00",
        "time_int": 47520,
        "user": "zjrenju88",
        "content": "L5"
    },
    {
        "action": "BACK",
        "time": "13:12:08",
        "time_int": 47528,
        "user": "GrandMaster",
        "content": ""
    },
    {
        "action": "MOVE",
        "time": "13:12:16",
        "time_int": 47536,
        "user": "GrandMaster",
        "content": "c5"
    },
    {
        "action": "TALK",
        "time": "13:12:26",
        "time_int": 47546,
        "user": "zjrenju88",
        "content": "哦K2"
    },
    {
        "action": "MOVE",
        "time": "13:12:32",
        "time_int": 47552,
        "user": "GrandMaster",
        "content": "b2"
    },
    {
        "action": "TALK",
        "time": "13:12:35",
        "time_int": 47555,
        "user": "zjrenju92",
        "content": "这个26 后 27 K2左右都杀"
    },
    {
        "action": "MOVE",
        "time": "13:12:37",
        "time_int": 47557,
        "user": "GrandMaster",
        "content": "65"
    },
    {
        "action": "MOVE",
        "time": "13:12:41",
        "time_int": 47561,
        "user": "GrandMaster",
        "content": "76"
    },
    {
        "action": "TALK",
        "time": "13:13:08",
        "time_int": 47588,
        "user": "GrandMaster",
        "content": "但是黑还是有两套真v"
    },
    {
        "action": "TALK",
        "time": "13:13:10",
        "time_int": 47590,
        "user": "GrandMaster",
        "content": "大家看到吗"
    },
    {
        "action": "TALK",
        "time": "13:13:16",
        "time_int": 47596,
        "user": "zjrenju50",
        "content": "NO"
    },
    {
        "action": "TALK",
        "time": "13:13:17",
        "time_int": 47597,
        "user": "zjrenju88",
        "content": "偶反映比较慢哈GM：）"
    },
    {
        "action": "TALK",
        "time": "13:13:19",
        "time_int": 47599,
        "user": "GrandMaster",
        "content": "j3，k3，还有n5这些点"
    },
    {
        "action": "TALK",
        "time": "13:13:25",
        "time_int": 47605,
        "user": "zjrenju12",
        "content": "右边看到一个"
    },
    {
        "action": "TALK",
        "time": "13:13:39",
        "time_int": 47619,
        "user": "zjrenju51",
        "content": "恩"
    },
    {
        "action": "TALK",
        "time": "13:13:40",
        "time_int": 47620,
        "user": "zjrenju12",
        "content": "看到两个"
    },
    {
        "action": "TALK",
        "time": "13:13:41",
        "time_int": 47621,
        "user": "zjrenju92",
        "content": "看到了"
    },
    {
        "action": "TALK",
        "time": "13:13:43",
        "time_int": 47623,
        "user": "zjrenju88",
        "content": "中间K3也杀"
    },
    {
        "action": "TALK",
        "time": "13:13:48",
        "time_int": 47628,
        "user": "zjrenju50",
        "content": "O"
    },
    {
        "action": "TALK",
        "time": "13:14:24",
        "time_int": 47664,
        "user": "zjrenju92",
        "content": "21那个眠三没用"
    },
    {
        "action": "TALK",
        "time": "13:14:24",
        "time_int": 47664,
        "user": "GrandMaster",
        "content": "所以这个26也是简单败。。"
    },
    {
        "action": "GOTO",
        "time": "13:14:33",
        "time_int": 47673,
        "user": "GrandMaster",
        "content": 25
    },
    {
        "action": "MOVE",
        "time": "13:14:37",
        "time_int": 47677,
        "user": "GrandMaster",
        "content": "c6"
    },
    {
        "action": "TALK",
        "time": "13:15:05",
        "time_int": 47705,
        "user": "GrandMaster",
        "content": "这样黑怎么来杀呢？"
    },
    {
        "action": "TALK",
        "time": "13:16:07",
        "time_int": 47767,
        "user": "zjrenju92",
        "content": "K5？"
    },
    {
        "action": "TALK",
        "time": "13:16:08",
        "time_int": 47768,
        "user": "zjrenju88",
        "content": "K5？"
    },
    {
        "action": "TALK",
        "time": "13:16:11",
        "time_int": 47771,
        "user": "GrandMaster",
        "content": "恩。"
    },
    {
        "action": "TALK",
        "time": "13:16:19",
        "time_int": 47779,
        "user": "Guest871",
        "content": "好复杂哦"
    },
    {
        "action": "TALK",
        "time": "13:16:19",
        "time_int": 47779,
        "user": "GrandMaster",
        "content": "看来大家现在的思路都很冷静啊"
    },
    {
        "action": "MOVE",
        "time": "13:16:21",
        "time_int": 47781,
        "user": "GrandMaster",
        "content": "b5"
    },
    {
        "action": "TALK",
        "time": "13:16:36",
        "time_int": 47796,
        "user": "zjrenju88",
        "content": "被简单杀怕了呗"
    },
    {
        "action": "TALK",
        "time": "13:16:56",
        "time_int": 47816,
        "user": "GrandMaster",
        "content": "一套h5的杀还有k4，k3，h3，j3，n3，l5"
    },
    {
        "action": "TALK",
        "time": "13:17:01",
        "time_int": 47821,
        "user": "GrandMaster",
        "content": "有了这两套vcf"
    },
    {
        "action": "TALK",
        "time": "13:17:14",
        "time_int": 47834,
        "user": "GrandMaster",
        "content": "就逼的白现在唯一只能先把黑h5的杀冲成长连"
    },
    {
        "action": "TALK",
        "time": "13:17:20",
        "time_int": 47840,
        "user": "GrandMaster",
        "content": "同时还不能活i5"
    },
    {
        "action": "MOVE",
        "time": "13:17:22",
        "time_int": 47842,
        "user": "GrandMaster",
        "content": "76"
    },
    {
        "action": "MOVE",
        "time": "13:17:26",
        "time_int": 47846,
        "user": "GrandMaster",
        "content": "65"
    },
    {
        "action": "TALK",
        "time": "13:17:51",
        "time_int": 47871,
        "user": "zjrenju92",
        "content": "对"
    },
    {
        "action": "TALK",
        "time": "13:17:59",
        "time_int": 47879,
        "user": "zjrenju92",
        "content": "那只有H5了"
    },
    {
        "action": "TALK",
        "time": "13:18:13",
        "time_int": 47893,
        "user": "GrandMaster",
        "content": "但是冲完之后黑又多了g4，h3这套杀"
    },
    {
        "action": "TALK",
        "time": "13:18:21",
        "time_int": 47901,
        "user": "GrandMaster",
        "content": "所以还是只能单防"
    },
    {
        "action": "MOVE",
        "time": "13:18:54",
        "time_int": 47934,
        "user": "GrandMaster",
        "content": "85"
    },
    {
        "action": "MOVE",
        "time": "13:18:58",
        "time_int": 47938,
        "user": "GrandMaster",
        "content": "c5"
    },
    {
        "action": "TALK",
        "time": "13:19:10",
        "time_int": 47950,
        "user": "GrandMaster",
        "content": "左边那套v白无论如何都防不出先手"
    },
    {
        "action": "TALK",
        "time": "13:19:16",
        "time_int": 47956,
        "user": "GrandMaster",
        "content": "那么黑右边只要有l5这个活三"
    },
    {
        "action": "TALK",
        "time": "13:19:17",
        "time_int": 47957,
        "user": "GrandMaster",
        "content": "就能杀"
    },
    {
        "action": "TALK",
        "time": "13:19:21",
        "time_int": 47961,
        "user": "wzqclass08",
        "content": "一套h5的杀还有k4，k3，h3，j3，n3，l5，这里的L5是433"
    },
    {
        "action": "TALK",
        "time": "13:20:16",
        "time_int": 48016,
        "user": "GrandMaster",
        "content": "我前面那样说的意思是对于白活i5来说的"
    },
    {
        "action": "TALK",
        "time": "13:20:32",
        "time_int": 48032,
        "user": "GrandMaster",
        "content": "要是单防"
    },
    {
        "action": "TALK",
        "time": "13:20:38",
        "time_int": 48038,
        "user": "GrandMaster",
        "content": "就像现在一样。 。黑很简单就能杀"
    },
    {
        "action": "TALK",
        "time": "13:20:45",
        "time_int": 48045,
        "user": "zjrenju92",
        "content": "是的！"
    },
    {
        "action": "TALK",
        "time": "13:20:47",
        "time_int": 48047,
        "user": "wzqclass08",
        "content": "哦"
    },
    {
        "action": "TALK",
        "time": "13:21:06",
        "time_int": 48066,
        "user": "GrandMaster",
        "content": "到这就没的防了。"
    },
    {
        "action": "GOTO",
        "time": "13:21:17",
        "time_int": 48077,
        "user": "GrandMaster",
        "content": 25
    },
    {
        "action": "TALK",
        "time": "13:21:26",
        "time_int": 48086,
        "user": "GrandMaster",
        "content": "大家对于这里26还有没有别的建议？"
    },
    {
        "action": "TALK",
        "time": "13:21:32",
        "time_int": 48092,
        "user": "zjrenju88",
        "content": "没有"
    },
    {
        "action": "TALK",
        "time": "13:21:39",
        "time_int": 48099,
        "user": "zjrenju12",
        "content": "没有了"
    },
    {
        "action": "TALK",
        "time": "13:21:52",
        "time_int": 48112,
        "user": "zjrenju92",
        "content": "没了"
    },
    {
        "action": "TALK",
        "time": "13:22:33",
        "time_int": 48153,
        "user": "zjrenju99",
        "content": "GM说说M6吧"
    },
    {
        "action": "MOVE",
        "time": "13:22:40",
        "time_int": 48160,
        "user": "GrandMaster",
        "content": "d6"
    },
    {
        "action": "TALK",
        "time": "13:23:05",
        "time_int": 48185,
        "user": "GrandMaster",
        "content": "这样再做k5就没有前面那套l5的杀了。"
    },
    {
        "action": "MOVE",
        "time": "13:23:16",
        "time_int": 48196,
        "user": "GrandMaster",
        "content": "b5"
    },
    {
        "action": "TALK",
        "time": "13:23:38",
        "time_int": 48218,
        "user": "zjrenju88",
        "content": "这样L5行不？"
    },
    {
        "action": "TALK",
        "time": "13:23:56",
        "time_int": 48236,
        "user": "GrandMaster",
        "content": "这里最后右边那个四三点不在l5了。如果白冲了活三的话"
    },
    {
        "action": "TALK",
        "time": "13:24:00",
        "time_int": 48240,
        "user": "GrandMaster",
        "content": "但是右边还是有套vcf"
    },
    {
        "action": "MOVE",
        "time": "13:24:32",
        "time_int": 48272,
        "user": "GrandMaster",
        "content": "76"
    },
    {
        "action": "MOVE",
        "time": "13:24:35",
        "time_int": 48275,
        "user": "GrandMaster",
        "content": "65"
    },
    {
        "action": "TALK",
        "time": "13:24:35",
        "time_int": 48275,
        "user": "weigui",
        "content": "这里的27是不是可以还到刚才的L5点"
    },
    {
        "action": "BACK",
        "time": "13:24:42",
        "time_int": 48282,
        "user": "GrandMaster",
        "content": ""
    },
    {
        "action": "BACK",
        "time": "13:24:45",
        "time_int": 48285,
        "user": "GrandMaster",
        "content": ""
    },
    {
        "action": "TALK",
        "time": "13:25:02",
        "time_int": 48302,
        "user": "zjrenju88",
        "content": "4242"
    },
    {
        "action": "BACK",
        "time": "13:25:23",
        "time_int": 48323,
        "user": "GrandMaster",
        "content": ""
    },
    {
        "action": "MOVE",
        "time": "13:25:26",
        "time_int": 48326,
        "user": "GrandMaster",
        "content": "c5"
    },
    {
        "action": "TALK",
        "time": "13:25:35",
        "time_int": 48335,
        "user": "zjrenju92",
        "content": "我个人认为这个26和L6的26 是一样的！"
    },
    {
        "action": "TALK",
        "time": "13:25:39",
        "time_int": 48339,
        "user": "GrandMaster",
        "content": "好象也可以"
    },
    {
        "action": "TALK",
        "time": "13:26:02",
        "time_int": 48362,
        "user": "GrandMaster",
        "content": "恩。。只要右边存在着通过h3这里饶到右边有套vcf存在"
    },
    {
        "action": "TALK",
        "time": "13:26:12",
        "time_int": 48372,
        "user": "GrandMaster",
        "content": "那么就是和26l6是一样的了。"
    },
    {
        "action": "TALK",
        "time": "13:26:45",
        "time_int": 48405,
        "user": "GrandMaster",
        "content": "这里做l5也是很多套vcf"
    },
    {
        "action": "TALK",
        "time": "13:27:12",
        "time_int": 48432,
        "user": "GrandMaster",
        "content": "大家看下，有没有防？"
    },
    {
        "action": "TALK",
        "time": "13:27:30",
        "time_int": 48450,
        "user": "zjrenju92",
        "content": "没"
    },
    {
        "action": "TALK",
        "time": "13:27:51",
        "time_int": 48471,
        "user": "zjrenju12",
        "content": "m4"
    },
    {
        "action": "MOVE",
        "time": "13:27:58",
        "time_int": 48478,
        "user": "GrandMaster",
        "content": "d4"
    },
    {
        "action": "MOVE",
        "time": "13:28:01",
        "time_int": 48481,
        "user": "GrandMaster",
        "content": "85"
    },
    {
        "action": "MOVE",
        "time": "13:28:05",
        "time_int": 48485,
        "user": "GrandMaster",
        "content": "74"
    },
    {
        "action": "MOVE",
        "time": "13:28:06",
        "time_int": 48486,
        "user": "GrandMaster",
        "content": "b5"
    },
    {
        "action": "MOVE",
        "time": "13:28:09",
        "time_int": 48489,
        "user": "GrandMaster",
        "content": "95"
    },
    {
        "action": "MOVE",
        "time": "13:28:12",
        "time_int": 48492,
        "user": "GrandMaster",
        "content": "c4"
    },
    {
        "action": "MOVE",
        "time": "13:28:15",
        "time_int": 48495,
        "user": "GrandMaster",
        "content": "c6"
    },
    {
        "action": "MOVE",
        "time": "13:28:18",
        "time_int": 48498,
        "user": "GrandMaster",
        "content": "d3"
    },
    {
        "action": "MOVE",
        "time": "13:28:21",
        "time_int": 48501,
        "user": "GrandMaster",
        "content": "e2"
    },
    {
        "action": "MOVE",
        "time": "13:28:24",
        "time_int": 48504,
        "user": "GrandMaster",
        "content": "b4"
    },
    {
        "action": "MOVE",
        "time": "13:28:28",
        "time_int": 48508,
        "user": "GrandMaster",
        "content": "d2"
    },
    {
        "action": "MOVE",
        "time": "13:28:33",
        "time_int": 48513,
        "user": "GrandMaster",
        "content": "b3"
    },
    {
        "action": "TALK",
        "time": "13:28:41",
        "time_int": 48521,
        "user": "zjrenju12",
        "content": "哦"
    },
    {
        "action": "TALK",
        "time": "13:28:44",
        "time_int": 48524,
        "user": "GrandMaster",
        "content": "太多vcf了。"
    },
    {
        "action": "GOTO",
        "time": "13:28:52",
        "time_int": 48532,
        "user": "GrandMaster",
        "content": 25
    },
    {
        "action": "TALK",
        "time": "13:29:36",
        "time_int": 48576,
        "user": "GrandMaster",
        "content": "如果单防左边也防不出先手。。那么右边简单做l5这种点就胜了。"
    },
    {
        "action": "TALK",
        "time": "13:30:10",
        "time_int": 48610,
        "user": "GrandMaster",
        "content": "没疑问了吧"
    },
    {
        "action": "TALK",
        "time": "13:30:17",
        "time_int": 48617,
        "user": "zjrenju12",
        "content": "没有"
    },
    {
        "action": "TALK",
        "time": "13:30:17",
        "time_int": 48617,
        "user": "zjrenju88",
        "content": "谢谢GM"
    },
    {
        "action": "BACK",
        "time": "13:30:17",
        "time_int": 48617,
        "user": "GrandMaster",
        "content": ""
    },
    {
        "action": "BACK",
        "time": "13:30:22",
        "time_int": 48622,
        "user": "GrandMaster",
        "content": ""
    },
    {
        "action": "BACK",
        "time": "13:30:25",
        "time_int": 48625,
        "user": "GrandMaster",
        "content": ""
    },
    {
        "action": "BACK",
        "time": "13:30:28",
        "time_int": 48628,
        "user": "GrandMaster",
        "content": ""
    },
    {
        "action": "BACK",
        "time": "13:30:32",
        "time_int": 48632,
        "user": "GrandMaster",
        "content": ""
    },
    {
        "action": "BACK",
        "time": "13:30:35",
        "time_int": 48635,
        "user": "GrandMaster",
        "content": ""
    },
    {
        "action": "BACK",
        "time": "13:30:39",
        "time_int": 48639,
        "user": "GrandMaster",
        "content": ""
    },
    {
        "action": "BACK",
        "time": "13:30:42",
        "time_int": 48642,
        "user": "GrandMaster",
        "content": ""
    },
    {
        "action": "TALK",
        "time": "13:31:19",
        "time_int": 48679,
        "user": "zjrenju92",
        "content": "。"
    },
    {
        "action": "TALK",
        "time": "13:31:40",
        "time_int": 48700,
        "user": "GrandMaster",
        "content": "接下来还有一个单防的点"
    },
    {
        "action": "MOVE",
        "time": "13:31:42",
        "time_int": 48702,
        "user": "GrandMaster",
        "content": "b6"
    },
    {
        "action": "TALK",
        "time": "13:31:47",
        "time_int": 48707,
        "user": "GrandMaster",
        "content": "就是k6这里。。"
    },
    {
        "action": "TALK",
        "time": "13:31:51",
        "time_int": 48711,
        "user": "GrandMaster",
        "content": "这个就留给大家当作业吧"
    },
    {
        "action": "TALK",
        "time": "13:31:56",
        "time_int": 48716,
        "user": "zjrenju50",
        "content": "。。。。。。。。。。。"
    },
    {
        "action": "TALK",
        "time": "13:31:57",
        "time_int": 48717,
        "user": "GrandMaster",
        "content": "今天的课就到这里。"
    },
    {
        "action": "TALK",
        "time": "13:31:59",
        "time_int": 48719,
        "user": "zjrenju88",
        "content": "辛苦辛苦：）3Q GM"
    },
    {
        "action": "TALK",
        "time": "13:32:22",
        "time_int": 48742,
        "user": "weigui",
        "content": "谢谢大家的参与，星期三见"
    },
    {
        "action": "TALK",
        "time": "13:32:25",
        "time_int": 48745,
        "user": "zjrenju92",
        "content": "喝口水拉"
    },
    {
        "action": "TALK",
        "time": "13:32:30",
        "time_int": 48750,
        "user": "zjrenju99",
        "content": "呵呵"
    },
    {
        "action": "TALK",
        "time": "13:32:32",
        "time_int": 48752,
        "user": "zjrenju18",
        "content": "谢谢"
    },
    {
        "action": "CHECKRESULT",
        "time": "13:32:40",
        "time_int": 48760,
        "user": "",
        "content": " zjrenju88, wzqclass08, zjrenju06, dittp, weigui, zjrenju99, zjrenju50, zjrenju18, tommy, zjrenju51, zjrenju17, zjrenju92."
    },
    {
        "action": "CREDIT",
        "time": "13:32:44",
        "time_int": 48764,
        "user": "",
        "content": " dittp, tommy, zjrenju17, zjrenju18, zjrenju88, zjrenju92."
    }
]